<?xml version="1.0" encoding="utf-8" ?>
<dwsync>
<file name="isabella.jpg" server="mckinleyrobotics.org//2011/" local="129424822662976760" remote="129436041600000000" />
<file name="jessica.jpg" server="mckinleyrobotics.org//2011/" local="129352319504349277" remote="129436042200000000" />
<file name="lisa.jpg" server="mckinleyrobotics.org//2011/" local="129424818188890857" remote="129436042200000000" />
<file name="sean.jpg" server="mckinleyrobotics.org//2011/" local="129379924336081368" remote="129436042200000000" />
<file name="austin.jpg" server="mckinleyrobotics.org//2011/" local="129379741779512559" remote="129436041600000000" />
<file name="eddie.jpg" server="mckinleyrobotics.org//2011/" local="129379720277732728" remote="129436041600000000" />
<file name="gilbert.jpg" server="mckinleyrobotics.org//2011/" local="129379718891513440" remote="129436041600000000" />
<file name="jarred.JPG" server="mckinleyrobotics.org//2011/" local="129379586339746466" remote="129436042200000000" />
<file name="jayna.jpg" server="mckinleyrobotics.org//2011/" local="129379756777890417" remote="129436042200000000" />
<file name="michelle.jpg" server="mckinleyrobotics.org//2011/" local="129424835170372142" remote="129436042200000000" />
<file name="weon.jpg" server="mckinleyrobotics.org//2011/" local="129379947251602061" remote="129436042200000000" />
<file name="youngri.jpg" server="mckinleyrobotics.org//2011/" local="129416142780000000" remote="129435336000000000" />
<file name="arnold.jpg" server="mckinleyrobotics.org/2012first/" local="129714336759147388" remote="129714345600000000" />
<file name="austin.jpg" server="mckinleyrobotics.org/2012first/" local="129714336763487636" remote="129714345600000000" />
<file name="benjamin.jpg" server="mckinleyrobotics.org/2012first/" local="129714336767847885" remote="129714345600000000" />
<file name="bobae.jpg" server="mckinleyrobotics.org/2012first/" local="129714336772598157" remote="129714345600000000" />
<file name="brian.jpg" server="mckinleyrobotics.org/2012first/" local="129714336782078699" remote="129714345600000000" />
<file name="carlos.jpg" server="mckinleyrobotics.org/2012first/" local="129714336792349287" remote="129714345600000000" />
<file name="darren.jpg" server="mckinleyrobotics.org/2012first/" local="129714336796539526" remote="129714345600000000" />
<file name="eddie.jpg" server="mckinleyrobotics.org/2012first/" local="129714336800799770" remote="129714345600000000" />
<file name="gilbert.jpg" server="mckinleyrobotics.org/2012first/" local="129714336805110017" remote="129714345600000000" />
<file name="isabella.jpg" server="mckinleyrobotics.org/2012first/" local="129714336809340259" remote="129714345600000000" />
<file name="jarred.jpg" server="mckinleyrobotics.org/2012first/" local="129714336820890919" remote="129714345600000000" />
<file name="jason.jpg" server="mckinleyrobotics.org/2012first/" local="129714336825441179" remote="129714345600000000" />
<file name="jayna.jpg" server="mckinleyrobotics.org/2012first/" local="129714336829401406" remote="129714345600000000" />
<file name="jessica.jpg" server="mckinleyrobotics.org/2012first/" local="129714336833631648" remote="129714345600000000" />
<file name="justin.jpg" server="mckinleyrobotics.org/2012first/" local="129714336837851889" remote="129714345600000000" />
<file name="kevin.jpg" server="mckinleyrobotics.org/2012first/" local="129714336842392149" remote="129714345600000000" />
<file name="kyle.jpg" server="mckinleyrobotics.org/2012first/" local="129714336850402607" remote="129714345600000000" />
<file name="lisa.jpg" server="mckinleyrobotics.org/2012first/" local="129714336855882921" remote="129714345600000000" />
<file name="maryc.jpg" server="mckinleyrobotics.org/2012first/" local="129714343162763654" remote="129714345600000000" />
<file name="maryl.jpg" server="mckinleyrobotics.org/2012first/" local="129714343480771843" remote="129714345600000000" />
<file name="michaelh.jpg" server="mckinleyrobotics.org/2012first/" local="129714336863283344" remote="129714345600000000" />
<file name="michaelk.jpg" server="mckinleyrobotics.org/2012first/" local="129714336866003499" remote="129714345600000000" />
<file name="michaels.jpg" server="mckinleyrobotics.org/2012first/" local="129714336868753657" remote="129714345600000000" />
<file name="michelle.jpg" server="mckinleyrobotics.org/2012first/" local="129714336871703826" remote="129714345600000000" />
<file name="nathan.jpg" server="mckinleyrobotics.org/2012first/" local="129714336874213969" remote="129714345600000000" />
<file name="sean.jpg" server="mckinleyrobotics.org/2012first/" local="129714336888974813" remote="129714345600000000" />
<file name="weon.jpg" server="mckinleyrobotics.org/2012first/" local="129714336893885094" remote="129714345600000000" />
<file name="youngri.jpg" server="mckinleyrobotics.org/2012first/" local="129734030880000000" remote="129734675400000000" />
<file name="thien.jpg" server="mckinleyrobotics.org/2012first/" local="129714336891414953" remote="129714345600000000" />
<file name="mary.jpg" server="mckinleyrobotics.org/2012first/" local="129714336859833147" remote="129714345600000000" />
<file name="arnold.jpg" server="mckinleyrobotics.org//2012test/" local="129714336750000000" remote="129740199600000000" />
<file name="austin.jpg" server="mckinleyrobotics.org//2012test/" local="129714336760000000" remote="129740199600000000" />
<file name="benjamin.jpg" server="mckinleyrobotics.org//2012test/" local="129714336760000000" remote="129740199600000000" />
<file name="bobae.jpg" server="mckinleyrobotics.org//2012test/" local="129714336770000000" remote="129740199600000000" />
<file name="brian.jpg" server="mckinleyrobotics.org//2012test/" local="129714336780000000" remote="129740199600000000" />
<file name="carlos.jpg" server="mckinleyrobotics.org//2012test/" local="129714336790000000" remote="129740199600000000" />
<file name="darren.jpg" server="mckinleyrobotics.org//2012test/" local="129714336790000000" remote="129740199600000000" />
<file name="eddie.jpg" server="mckinleyrobotics.org//2012test/" local="129714336800000000" remote="129740199600000000" />
<file name="gilbert.jpg" server="mckinleyrobotics.org//2012test/" local="129714336800000000" remote="129740199600000000" />
<file name="isabella.jpg" server="mckinleyrobotics.org//2012test/" local="129714336800000000" remote="129740199600000000" />
<file name="jarred.jpg" server="mckinleyrobotics.org//2012test/" local="129714336820000000" remote="129740199600000000" />
<file name="jason.jpg" server="mckinleyrobotics.org//2012test/" local="129714336820000000" remote="129740199600000000" />
<file name="jayna.jpg" server="mckinleyrobotics.org//2012test/" local="129714336820000000" remote="129740199600000000" />
<file name="jessica.jpg" server="mckinleyrobotics.org//2012test/" local="129714336830000000" remote="129740199600000000" />
<file name="justin.jpg" server="mckinleyrobotics.org//2012test/" local="129714336830000000" remote="129740199600000000" />
<file name="kevin.jpg" server="mckinleyrobotics.org//2012test/" local="129714336840000000" remote="129740199600000000" />
<file name="kyle.jpg" server="mckinleyrobotics.org//2012test/" local="129714336850000000" remote="129740199600000000" />
<file name="lisa.jpg" server="mckinleyrobotics.org//2012test/" local="129714336850000000" remote="129740199600000000" />
<file name="mary.jpg" server="mckinleyrobotics.org//2012test/" local="129714336850000000" remote="129740199600000000" />
<file name="maryc.jpg" server="mckinleyrobotics.org//2012test/" local="129714343160000000" remote="129740199600000000" />
<file name="maryl.jpg" server="mckinleyrobotics.org//2012test/" local="129714343480000000" remote="129740199600000000" />
<file name="michaelh.jpg" server="mckinleyrobotics.org//2012test/" local="129714336860000000" remote="129740199600000000" />
<file name="michaelk.jpg" server="mckinleyrobotics.org//2012test/" local="129714336860000000" remote="129740199600000000" />
<file name="michaels.jpg" server="mckinleyrobotics.org//2012test/" local="129714336860000000" remote="129740199600000000" />
<file name="michelle.jpg" server="mckinleyrobotics.org//2012test/" local="129714336870000000" remote="129740199600000000" />
<file name="nathan.jpg" server="mckinleyrobotics.org//2012test/" local="129714336870000000" remote="129740199600000000" />
<file name="sean.jpg" server="mckinleyrobotics.org//2012test/" local="129714336880000000" remote="129740199600000000" />
<file name="thien.jpg" server="mckinleyrobotics.org//2012test/" local="129714336890000000" remote="129740199600000000" />
<file name="weon.jpg" server="mckinleyrobotics.org//2012test/" local="129714336890000000" remote="129740199600000000" />
<file name="youngri.jpg" server="mckinleyrobotics.org//2012test/" local="129734030889105969" remote="129739464000000000" />
<file name="arnold.jpg" server="mckinleyrobotics.org//2012first/" local="129714336750000000" remote="129733288200000000" />
<file name="austin.jpg" server="mckinleyrobotics.org//2012first/" local="129714336760000000" remote="129733288200000000" />
<file name="benjamin.jpg" server="mckinleyrobotics.org//2012first/" local="129714336760000000" remote="129733288200000000" />
<file name="bobae.jpg" server="mckinleyrobotics.org//2012first/" local="129714336770000000" remote="129733288200000000" />
<file name="brian.jpg" server="mckinleyrobotics.org//2012first/" local="129714336780000000" remote="129733288200000000" />
<file name="carlos.jpg" server="mckinleyrobotics.org//2012first/" local="129714336790000000" remote="129733288200000000" />
<file name="darren.jpg" server="mckinleyrobotics.org//2012first/" local="129714336790000000" remote="129733288200000000" />
<file name="eddie.jpg" server="mckinleyrobotics.org//2012first/" local="129714336800000000" remote="129733288200000000" />
<file name="gilbert.jpg" server="mckinleyrobotics.org//2012first/" local="129714336800000000" remote="129733288200000000" />
<file name="isabella.jpg" server="mckinleyrobotics.org//2012first/" local="129714336800000000" remote="129733288200000000" />
<file name="jarred.jpg" server="mckinleyrobotics.org//2012first/" local="129714336820000000" remote="129733288200000000" />
<file name="jason.jpg" server="mckinleyrobotics.org//2012first/" local="129714336820000000" remote="129733288200000000" />
<file name="jayna.jpg" server="mckinleyrobotics.org//2012first/" local="129714336820000000" remote="129733288200000000" />
<file name="jessica.jpg" server="mckinleyrobotics.org//2012first/" local="129714336830000000" remote="129733288200000000" />
<file name="justin.jpg" server="mckinleyrobotics.org//2012first/" local="129714336830000000" remote="129733288200000000" />
<file name="kevin.jpg" server="mckinleyrobotics.org//2012first/" local="129714336840000000" remote="129733288200000000" />
<file name="kyle.jpg" server="mckinleyrobotics.org//2012first/" local="129714336850000000" remote="129733288200000000" />
<file name="lisa.jpg" server="mckinleyrobotics.org//2012first/" local="129714336850000000" remote="129733288200000000" />
<file name="mary.jpg" server="mckinleyrobotics.org//2012first/" local="129714336850000000" remote="129733288200000000" />
<file name="maryc.jpg" server="mckinleyrobotics.org//2012first/" local="129714343160000000" remote="129733288200000000" />
<file name="maryl.jpg" server="mckinleyrobotics.org//2012first/" local="129714343480000000" remote="129733288200000000" />
<file name="michaelh.jpg" server="mckinleyrobotics.org//2012first/" local="129714336860000000" remote="129733288200000000" />
<file name="michaelk.jpg" server="mckinleyrobotics.org//2012first/" local="129714336860000000" remote="129733288200000000" />
<file name="michaels.jpg" server="mckinleyrobotics.org//2012first/" local="129714336860000000" remote="129733288200000000" />
<file name="michelle.jpg" server="mckinleyrobotics.org//2012first/" local="129714336870000000" remote="129733288200000000" />
<file name="nathan.jpg" server="mckinleyrobotics.org//2012first/" local="129714336870000000" remote="129733288200000000" />
<file name="sean.jpg" server="mckinleyrobotics.org//2012first/" local="129714336880000000" remote="129733288200000000" />
<file name="thien.jpg" server="mckinleyrobotics.org//2012first/" local="129714336890000000" remote="129733288200000000" />
<file name="weon.jpg" server="mckinleyrobotics.org//2012first/" local="129714336890000000" remote="129733288200000000" />
<file name="youngri.jpg" server="mckinleyrobotics.org//2012first/" local="129734030889105969" remote="129734070000000000" />
</dwsync>